<?xml version="1.0" encoding="utf-8" ?>
<control xmlns:def="Definition" xmlns="http://schemas.sitecore.net/Visual-Studio-Intellisense">
  <Installer.BuildPackage>
    <WizardForm CodeBeside="Sitecore.Shell.Applications.Install.Dialogs.BuildPackage,Sitecore.Client">

      <WizardFormPage ID="SetName" Header="Package Name" Text="Enter a name for the package. Click Next to continue." Icon="People/32x32/Box_Software.png">
        <WizardFormIndent>
          <Literal class="scFieldLabel" Text="Package name:"/>
          <Edit ID="PackageFile" Width="100%" maxlength="200"/>
        </WizardFormIndent>
      </WizardFormPage>

      <WizardFormProgressPage ID="Building" Header="Building" Text="This may take a few minutes." ActionText="Generating..." Icon="People/32x32/Box_Software.png">
        <TaskMonitor ID="Monitor" />
      </WizardFormProgressPage>

      <WizardFormPage ID="LastPage" Icon="People/32x32/Box_Software.png">
        <WizardFormIndent>
          <Border ID="SuccessMessage">
            <Literal class="scFieldLabel sc-text-largevalue" Text="The package has been built successfully."/>
            <Border class="scFieldLabel">
              <Literal Text="Click this button to download the package:"/>
              <Toolbutton Icon="Network/16x16/download.png" Tooltip="Download the package" Click="buildpackage:download"/>
            </Border>
          </Border>

          <Border ID="FailureMessage" Style="color:#ca241c;display:none">
          </Border>
        </WizardFormIndent>
      </WizardFormPage>

    </WizardForm>
  </Installer.BuildPackage>
</control>
